ArtexConfigure/__init__.py
ArtexConfigure/conf.py
ArtexConfigure-0.0.1.dist-info/LICENSE
ArtexConfigure-0.0.1.dist-info/METADATA
ArtexConfigure-0.0.1.dist-info/WHEEL
ArtexConfigure-0.0.1.dist-info/top_level.txt
ArtexConfigure-0.0.1.dist-info/RECORD
