Metadata-Version: 2.1
Name: ArtexConfigure
Version: 0.0.1
Summary: A python library that writes your configuration into an .ini file
Home-page: https://github.com/JunaidParkar/ArtexConfigure
Author: Artex AI
Project-URL: Documentation, https://github.com/JunaidParkar/ArtexConfigure
Project-URL: Source, https://github.com/JunaidParkar/ArtexConfigure
Project-URL: Tracker, https://github.com/JunaidParkar/ArtexConfigure
Classifier: Programming Language :: Python :: 3
Classifier: License :: OSI Approved :: Boost Software License 1.0 (BSL-1.0)
Classifier: Operating System :: OS Independent
Requires-Python: >=3.6
License-File: LICENSE
Requires-Dist: configparser
